[{"company":"Schultz-Bernhard","position":"Help Desk Operator","status":"interview","jobType":"remote","createdBy":"654a1453a5d0d30e380df43a","createdAt":"2023-03-02T03:43:32Z"},
{"company":"Fritsch, Bernier and Graham","position":"Sales Associate","status":"pending","jobType":"remote","createdBy":"654a1453a5d0d30e380df43a","createdAt":"2023-05-13T02:28:01Z"},
{"company":"Davis, VonRueden and Prosacco","position":"Research Associate","status":"pending","jobType":"internship","createdBy":"654a1453a5d0d30e380df43a","createdAt":"2022-12-19T16:18:48Z"},
{"company":"Kuphal, Kub and Block","position":"Internal Auditor","status":"declined","jobType":"internship","createdBy":"654a1453a5d0d30e380df43a","createdAt":"2023-04-14T21:22:25Z"},
{"company":"Streich Inc","position":"Social Worker","status":"pending","jobType":"full-time","createdBy":"654a1453a5d0d30e380df43a","createdAt":"2022-12-06T11:17:03Z"},
{"company":"Heaney Group","position":"Junior Executive","status":"interview","jobType":"full-time","createdBy":"654a1453a5d0d30e380df43a","createdAt":"2023-06-16T07:02:02Z"},
{"company":"Batz-Stracke","position":"Recruiting Manager","status":"declined","jobType":"part-time","createdBy":"654a1453a5d0d30e380df43a","createdAt":"2022-12-30T10:53:29Z"},
{"company":"Glover-Bauch","position":"Senior Cost Accountant","status":"declined","jobType":"full-time","createdBy":"654a1453a5d0d30e380df43a","createdAt":"2023-02-10T06:38:12Z"},
{"company":"Mayert-Rutherford","position":"Assistant Manager","status":"declined","jobType":"internship","createdBy":"654a1453a5d0d30e380df43a","createdAt":"2023-02-06T23:58:53Z"},
{"company":"Balistreri LLC","position":"General Manager","status":"interview","jobType":"full-time","createdBy":"654a1453a5d0d30e380df43a","createdAt":"2023-05-02T19:15:45Z"},
{"company":"Veum, Shields and Weimann","position":"Environmental Specialist","status":"declined","jobType":"full-time","createdBy":"654a1453a5d0d30e380df43a","createdAt":"2023-07-13T17:37:22Z"},
{"company":"Koepp LLC","position":"Accountant III","status":"pending","jobType":"part-time","createdBy":"654a1453a5d0d30e380df43a","createdAt":"2023-01-25T01:25:55Z"},
{"company":"Gleason and Sons","position":"Marketing Assistant","status":"interview","jobType":"remote","createdBy":"654a1453a5d0d30e380df43a","createdAt":"2023-03-23T18:00:28Z"},
{"company":"Hermann, Murphy and Robel","position":"Administrative Officer","status":"declined","jobType":"full-time","createdBy":"654a1453a5d0d30e380df43a","createdAt":"2023-07-23T03:53:14Z"},
{"company":"Boyle-Hackett","position":"VP Accounting","status":"interview","jobType":"internship","createdBy":"654a1453a5d0d30e380df43a","createdAt":"2023-06-08T02:51:24Z"},
{"company":"Collier LLC","position":"Director of Sales","status":"declined","jobType":"full-time","createdBy":"654a1453a5d0d30e380df43a","createdAt":"2023-10-29T14:48:37Z"},
{"company":"D'Amore-Gerhold","position":"Senior Quality Engineer","status":"declined","jobType":"full-time","createdBy":"654a1453a5d0d30e380df43a","createdAt":"2023-09-27T01:24:48Z"},
{"company":"MacGyver, Boyer and Cartwright","position":"Systems Administrator I","status":"declined","jobType":"remote","createdBy":"654a1453a5d0d30e380df43a","createdAt":"2023-07-08T13:05:50Z"},
{"company":"Sawayn-Rath","position":"Senior Financial Analyst","status":"declined","jobType":"part-time","createdBy":"654a1453a5d0d30e380df43a","createdAt":"2023-10-20T06:43:19Z"},
{"company":"Hickle-Schumm","position":"Physical Therapy Assistant","status":"declined","jobType":"internship","createdBy":"654a1453a5d0d30e380df43a","createdAt":"2023-01-20T05:52:06Z"},
{"company":"Hodkiewicz LLC","position":"General Manager","status":"interview","jobType":"internship","createdBy":"654a1453a5d0d30e380df43a","createdAt":"2023-04-25T17:31:07Z"},
{"company":"McLaughlin-Gutmann","position":"Analyst Programmer","status":"interview","jobType":"part-time","createdBy":"654a1453a5d0d30e380df43a","createdAt":"2022-12-30T17:51:40Z"},
{"company":"Nitzsche Inc","position":"VP Marketing","status":"interview","jobType":"part-time","createdBy":"654a1453a5d0d30e380df43a","createdAt":"2023-09-13T11:49:26Z"},
{"company":"Emmerich, Zboncak and Greenfelder","position":"Mechanical Systems Engineer","status":"interview","jobType":"remote","createdBy":"654a1453a5d0d30e380df43a","createdAt":"2022-12-19T17:57:21Z"},
{"company":"Keebler and Sons","position":"Recruiter","status":"declined","jobType":"full-time","createdBy":"654a1453a5d0d30e380df43a","createdAt":"2022-12-12T02:28:09Z"},
{"company":"Ryan Group","position":"Nurse Practicioner","status":"interview","jobType":"full-time","createdBy":"654a1453a5d0d30e380df43a","createdAt":"2023-07-23T04:02:51Z"},
{"company":"Williamson LLC","position":"Assistant Professor","status":"declined","jobType":"full-time","createdBy":"654a1453a5d0d30e380df43a","createdAt":"2023-06-27T05:00:17Z"},
{"company":"Jakubowski, Kshlerin and Stracke","position":"Software Consultant","status":"interview","jobType":"remote","createdBy":"654a1453a5d0d30e380df43a","createdAt":"2023-03-16T21:02:19Z"},
{"company":"Corwin, Doyle and Oberbrunner","position":"Account Executive","status":"pending","jobType":"full-time","createdBy":"654a1453a5d0d30e380df43a","createdAt":"2023-03-26T20:16:15Z"},
{"company":"Boyer-Vandervort","position":"Account Coordinator","status":"interview","jobType":"internship","createdBy":"654a1453a5d0d30e380df43a","createdAt":"2022-11-22T15:20:52Z"},
{"company":"Price-Hartmann","position":"Design Engineer","status":"pending","jobType":"remote","createdBy":"654a1453a5d0d30e380df43a","createdAt":"2023-02-17T20:47:30Z"},
{"company":"Spinka, Crist and Barrows","position":"VP Product Management","status":"declined","jobType":"part-time","createdBy":"654a1453a5d0d30e380df43a","createdAt":"2023-07-23T07:00:09Z"},
{"company":"Hudson-Mante","position":"Staff Accountant IV","status":"interview","jobType":"part-time","createdBy":"654a1453a5d0d30e380df43a","createdAt":"2023-07-14T12:01:20Z"},
{"company":"Donnelly, Miller and Stark","position":"Engineer II","status":"pending","jobType":"internship","createdBy":"654a1453a5d0d30e380df43a","createdAt":"2022-12-13T23:09:16Z"},
{"company":"Friesen, Moen and Armstrong","position":"Recruiter","status":"declined","jobType":"internship","createdBy":"654a1453a5d0d30e380df43a","createdAt":"2023-11-03T00:05:35Z"},
{"company":"Hackett Group","position":"Structural Engineer","status":"pending","jobType":"internship","createdBy":"654a1453a5d0d30e380df43a","createdAt":"2023-04-10T03:57:04Z"},
{"company":"Kirlin, Paucek and Farrell","position":"Financial Advisor","status":"pending","jobType":"remote","createdBy":"654a1453a5d0d30e380df43a","createdAt":"2023-04-27T17:24:49Z"},
{"company":"Kuhic, Mertz and Walsh","position":"Web Developer III","status":"pending","jobType":"full-time","createdBy":"654a1453a5d0d30e380df43a","createdAt":"2023-03-28T04:43:58Z"},
{"company":"Armstrong-Goldner","position":"Health Coach III","status":"declined","jobType":"remote","createdBy":"654a1453a5d0d30e380df43a","createdAt":"2023-05-14T08:58:05Z"},
{"company":"Haag Inc","position":"Developer IV","status":"pending","jobType":"full-time","createdBy":"654a1453a5d0d30e380df43a","createdAt":"2023-07-28T20:40:45Z"},
{"company":"Langworth and Sons","position":"Account Representative III","status":"pending","jobType":"remote","createdBy":"654a1453a5d0d30e380df43a","createdAt":"2022-11-24T03:51:56Z"},
{"company":"Ebert Group","position":"Librarian","status":"declined","jobType":"part-time","createdBy":"654a1453a5d0d30e380df43a","createdAt":"2023-03-18T06:43:51Z"},
{"company":"Hessel-Bradtke","position":"Analog Circuit Design manager","status":"declined","jobType":"remote","createdBy":"654a1453a5d0d30e380df43a","createdAt":"2023-09-23T23:03:12Z"},
{"company":"Satterfield, Walker and Labadie","position":"Information Systems Manager","status":"pending","jobType":"part-time","createdBy":"654a1453a5d0d30e380df43a","createdAt":"2022-12-30T02:58:35Z"},
{"company":"Erdman, Rowe and O'Keefe","position":"Programmer III","status":"interview","jobType":"part-time","createdBy":"654a1453a5d0d30e380df43a","createdAt":"2023-10-19T18:15:35Z"},
{"company":"Leuschke-Greenfelder","position":"Data Coordinator","status":"pending","jobType":"internship","createdBy":"654a1453a5d0d30e380df43a","createdAt":"2023-01-03T12:53:01Z"},
{"company":"Bahringer Group","position":"Project Manager","status":"pending","jobType":"full-time","createdBy":"654a1453a5d0d30e380df43a","createdAt":"2023-06-13T14:31:09Z"},
{"company":"Hoeger, Grant and Casper","position":"Cost Accountant","status":"declined","jobType":"part-time","createdBy":"654a1453a5d0d30e380df43a","createdAt":"2023-02-28T07:30:49Z"},
{"company":"Wolff-Will","position":"Marketing Manager","status":"interview","jobType":"full-time","createdBy":"654a1453a5d0d30e380df43a","createdAt":"2022-11-14T22:49:30Z"},
{"company":"Hickle-Rempel","position":"Financial Advisor","status":"pending","jobType":"remote","createdBy":"654a1453a5d0d30e380df43a","createdAt":"2023-01-27T21:22:43Z"},
{"company":"Shields Inc","position":"Help Desk Operator","status":"pending","jobType":"internship","createdBy":"654a1453a5d0d30e380df43a","createdAt":"2023-05-08T05:43:18Z"},
{"company":"Erdman, McDermott and Collier","position":"Programmer Analyst II","status":"interview","jobType":"remote","createdBy":"654a1453a5d0d30e380df43a","createdAt":"2023-07-31T14:25:44Z"},
{"company":"Lockman, Anderson and Stark","position":"Analyst Programmer","status":"interview","jobType":"remote","createdBy":"654a1453a5d0d30e380df43a","createdAt":"2023-07-04T05:39:58Z"},
{"company":"McGlynn, Runolfsdottir and Ortiz","position":"Human Resources Assistant II","status":"declined","jobType":"internship","createdBy":"654a1453a5d0d30e380df43a","createdAt":"2023-10-13T21:02:48Z"},
{"company":"Hills-Schuster","position":"Professor","status":"declined","jobType":"internship","createdBy":"654a1453a5d0d30e380df43a","createdAt":"2023-09-22T18:58:38Z"},
{"company":"Rolfson and Sons","position":"Help Desk Operator","status":"pending","jobType":"part-time","createdBy":"654a1453a5d0d30e380df43a","createdAt":"2023-01-26T01:19:42Z"},
{"company":"Skiles-Dicki","position":"Health Coach I","status":"interview","jobType":"internship","createdBy":"654a1453a5d0d30e380df43a","createdAt":"2023-10-14T23:48:33Z"},
{"company":"Robel Group","position":"Quality Control Specialist","status":"pending","jobType":"part-time","createdBy":"654a1453a5d0d30e380df43a","createdAt":"2023-01-13T08:11:21Z"},
{"company":"Kreiger and Sons","position":"Research Assistant IV","status":"interview","jobType":"part-time","createdBy":"654a1453a5d0d30e380df43a","createdAt":"2023-06-03T20:20:37Z"},
{"company":"Lang and Sons","position":"Accounting Assistant I","status":"declined","jobType":"full-time","createdBy":"654a1453a5d0d30e380df43a","createdAt":"2022-11-13T11:22:07Z"},
{"company":"Lemke, Beer and Howell","position":"Sales Representative","status":"pending","jobType":"remote","createdBy":"654a1453a5d0d30e380df43a","createdAt":"2023-06-29T04:03:58Z"},
{"company":"Rutherford LLC","position":"Office Assistant IV","status":"pending","jobType":"full-time","createdBy":"654a1453a5d0d30e380df43a","createdAt":"2023-08-02T13:21:58Z"},
{"company":"Block, Kreiger and Klocko","position":"Human Resources Manager","status":"pending","jobType":"part-time","createdBy":"654a1453a5d0d30e380df43a","createdAt":"2023-04-23T07:25:12Z"},
{"company":"Hettinger, Howe and Becker","position":"Health Coach I","status":"interview","jobType":"full-time","createdBy":"654a1453a5d0d30e380df43a","createdAt":"2022-11-28T21:10:59Z"},
{"company":"Gleichner-Huel","position":"Recruiter","status":"pending","jobType":"remote","createdBy":"654a1453a5d0d30e380df43a","createdAt":"2022-12-21T06:59:03Z"},
{"company":"Runte, Blanda and Cruickshank","position":"Research Nurse","status":"interview","jobType":"remote","createdBy":"654a1453a5d0d30e380df43a","createdAt":"2022-12-27T19:45:15Z"},
{"company":"Stark, Feil and O'Reilly","position":"Environmental Specialist","status":"declined","jobType":"internship","createdBy":"654a1453a5d0d30e380df43a","createdAt":"2023-01-18T00:19:43Z"},
{"company":"Witting, Bradtke and O'Connell","position":"Social Worker","status":"pending","jobType":"full-time","createdBy":"654a1453a5d0d30e380df43a","createdAt":"2023-10-27T19:16:55Z"},
{"company":"Zboncak and Sons","position":"Health Coach IV","status":"pending","jobType":"full-time","createdBy":"654a1453a5d0d30e380df43a","createdAt":"2023-04-02T05:27:02Z"},
{"company":"Schroeder, Mann and Dooley","position":"Technical Writer","status":"interview","jobType":"remote","createdBy":"654a1453a5d0d30e380df43a","createdAt":"2023-02-09T15:19:39Z"},
{"company":"Gutmann-Russel","position":"Account Coordinator","status":"pending","jobType":"remote","createdBy":"654a1453a5d0d30e380df43a","createdAt":"2023-09-02T07:34:36Z"},
{"company":"Ritchie Inc","position":"Environmental Specialist","status":"interview","jobType":"remote","createdBy":"654a1453a5d0d30e380df43a","createdAt":"2023-03-19T19:13:45Z"},
{"company":"Dietrich, Schamberger and Dibbert","position":"Senior Developer","status":"pending","jobType":"full-time","createdBy":"654a1453a5d0d30e380df43a","createdAt":"2023-08-04T10:13:22Z"},
{"company":"Lockman and Sons","position":"Associate Professor","status":"interview","jobType":"full-time","createdBy":"654a1453a5d0d30e380df43a","createdAt":"2023-10-04T11:54:54Z"},
{"company":"Lueilwitz, Funk and Dare","position":"Project Manager","status":"interview","jobType":"part-time","createdBy":"654a1453a5d0d30e380df43a","createdAt":"2022-12-16T03:35:32Z"}]